{
  "packages": {
    "childe": null,
    "i3-wm": {
      "ref": "main",
      "source": "https://github.com/regolith-linux/i3-wm.git"
    },
    "i3status-rs": {
      "ref": "ubuntu/v0.22.0",
      "source": "https://github.com/regolith-linux/i3status-rs_debian.git"
    },
    "regolith-control-center": {
      "ref": "ubuntu/jammy",
      "source": "https://github.com/regolith-linux/regolith-control-center.git"
    },
    "regolith-session": {
      "ref": "debian-bookworm",
      "source": "https://github.com/regolith-linux/regolith-session.git"
    },
    "regolith-sway-touchpad-gestures": null,
    "sway-regolith": {
      "ref": "packaging/v1.7-regolith",
      "source": "https://github.com/regolith-linux/sway-regolith.git"
    },
    "xdg-desktop-portal-regolith": {
      "ref": "ubuntu/jammy",
      "source": "https://github.com/regolith-linux/xdg-desktop-portal-regolith.git"
    }
  }
}
